sksmithy/__init__.py
sksmithy/__main__.py
sksmithy/_arguments.py
sksmithy/_callbacks.py
sksmithy/_logger.py
sksmithy/_models.py
sksmithy/_parsers.py
sksmithy/_prompts.py
sksmithy/_utils.py
sksmithy/app.py
sksmithy/cli.py
sksmithy/py.typed
sksmithy/_static/description.md
sksmithy/_static/template.py.jinja
sksmithy/_static/tui.tcss
sksmithy/tui/__init__.py
sksmithy/tui/_components.py
sksmithy/tui/_tui.py
sksmithy/tui/_validators.py
sklearn_smithy-0.2.0.dist-info/METADATA
sklearn_smithy-0.2.0.dist-info/WHEEL
sklearn_smithy-0.2.0.dist-info/entry_points.txt
sklearn_smithy-0.2.0.dist-info/licenses/LICENSE
sklearn_smithy-0.2.0.dist-info/RECORD
