Metadata-Version: 2.3
Name: sklearn-smithy
Version: 0.2.0
Summary: Toolkit to forge scikit-learn compatible estimators.
Project-URL: Repository, https://github.com/FBruzzesi/sklearn-smithy
Project-URL: Issues, https://github.com/FBruzzesi/sklearn-smithy/issues
Project-URL: Documentation, https://fbruzzesi.github.io/sklearn-smithy
Project-URL: Website, https://sklearn-smithy.streamlit.app/
Author: Francesco Bruzzesi
License: MIT License
License-File: LICENSE
Keywords: cli,data-science,machine-learning,python,scikit-learn,tui,webui
Classifier: Development Status :: 4 - Beta
Classifier: License :: OSI Approved :: MIT License
Classifier: Programming Language :: Python :: 3
Classifier: Programming Language :: Python :: 3.10
Classifier: Programming Language :: Python :: 3.11
Classifier: Programming Language :: Python :: 3.12
Classifier: Topic :: Software Development :: Libraries :: Python Modules
Classifier: Typing :: Typed
Requires-Python: >=3.10
Requires-Dist: jinja2>=3.0.0
Requires-Dist: result>=0.16.0
Requires-Dist: rich>=13.0.0
Requires-Dist: ruff>=0.4.0
Requires-Dist: typer>=0.12.0
Provides-Extra: all
Requires-Dist: streamlit>=1.34.0; extra == 'all'
Requires-Dist: textual>=0.65.0; extra == 'all'
Provides-Extra: streamlit
Requires-Dist: streamlit>=1.34.0; extra == 'streamlit'
Provides-Extra: textual
Requires-Dist: textual[syntax]>=0.65.0; extra == 'textual'
